{
    "1": "1",
    "2": "block_start",
    "3": "instruction_term_1",
    "4": "instruction_term_2",
    "5": "fixation",
    "19": "termination",
    "21": "confidence_slider",
    "22": "outcome_win",
    "23": "outcome_loss",
    "24": "outcome_ND",
    "31": "button_press_L",
    "32": "button_press_R",
    "66": "block_break",
    "69": "experiment_start",
    "96": "experiment_end",
    "100": "cue_term_1_0",
    "101": "cue_term_1_1",
    "102": "cue_term_1_2",
    "103": "cue_term_1_3",
    "104": "cue_term_1_4",
    "190": "block_number_0",
    "191": "block_number_1",
    "192": "block_number_2",
    "193": "block_number_3",
    "194": "block_number_4",
    "200": "game_number_0",
    "201": "game_number_1",
    "202": "game_number_2",
    "203": "game_number_3",
    "204": "game_number_4",
    "205": "game_number_5",
    "206": "game_number_6",
    "207": "game_number_7",
    "208": "game_number_8",
    "209": "game_number_9",
    "210": "game_number_10",
    "211": "game_number_11",
    "212": "game_number_12",
    "213": "game_number_13",
    "214": "game_number_14",
    "215": "game_number_15",
    "216": "game_number_16",
    "217": "game_number_17",
    "218": "game_number_18",
    "219": "game_number_19",
    "220": "game_number_20",
    "221": "game_number_21",
    "222": "game_number_22",
    "223": "game_number_23",
    "224": "game_number_24",
    "225": "game_number_25",
    "226": "game_number_26",
    "227": "game_number_27",
    "228": "game_number_28",
    "229": "game_number_29",
    "230": "game_number_30",
    "231": "game_number_31",
    "232": "game_number_32",
    "233": "game_number_33",
    "234": "game_number_34",
    "235": "game_number_35",
    "236": "game_number_36",
    "237": "game_number_37",
    "238": "game_number_38",
    "239": "game_number_39",
    "240": "game_number_40"
}